lnbits/__init__.py
lnbits/__main__.py
lnbits/app.py
lnbits/bolt11.py
lnbits/commands.py
lnbits/db.py
lnbits/decorators.py
lnbits/exceptions.py
lnbits/helpers.py
lnbits/jinja2_templating.py
lnbits/middleware.py
lnbits/py.typed
lnbits/server.py
lnbits/settings.py
lnbits/tasks.py
lnbits/core/__init__.py
lnbits/core/db.py
lnbits/core/helpers.py
lnbits/core/migrations.py
lnbits/core/tasks.py
lnbits/core/crud/__init__.py
lnbits/core/crud/assets.py
lnbits/core/crud/audit.py
lnbits/core/crud/db_versions.py
lnbits/core/crud/extensions.py
lnbits/core/crud/payments.py
lnbits/core/crud/settings.py
lnbits/core/crud/tinyurl.py
lnbits/core/crud/users.py
lnbits/core/crud/wallets.py
lnbits/core/crud/webpush.py
lnbits/core/models/__init__.py
lnbits/core/models/assets.py
lnbits/core/models/audit.py
lnbits/core/models/extensions.py
lnbits/core/models/extensions_builder.py
lnbits/core/models/lnurl.py
lnbits/core/models/misc.py
lnbits/core/models/notifications.py
lnbits/core/models/payments.py
lnbits/core/models/tinyurl.py
lnbits/core/models/users.py
lnbits/core/models/wallets.py
lnbits/core/models/webpush.py
lnbits/core/models/sso/keycloak.py
lnbits/core/services/__init__.py
lnbits/core/services/assets.py
lnbits/core/services/extensions.py
lnbits/core/services/extensions_builder.py
lnbits/core/services/fiat_providers.py
lnbits/core/services/funding_source.py
lnbits/core/services/lnurl.py
lnbits/core/services/nostr.py
lnbits/core/services/notifications.py
lnbits/core/services/payments.py
lnbits/core/services/settings.py
lnbits/core/services/users.py
lnbits/core/services/wallets.py
lnbits/core/services/websockets.py
lnbits/core/templates/index.html
lnbits/core/templates/index_public.html
lnbits/core/templates/service-worker.js
lnbits/core/views/__init__.py
lnbits/core/views/admin_api.py
lnbits/core/views/api.py
lnbits/core/views/asset_api.py
lnbits/core/views/audit_api.py
lnbits/core/views/auth_api.py
lnbits/core/views/callback_api.py
lnbits/core/views/extension_api.py
lnbits-1.4.1.dist-info/METADATA
lnbits-1.4.1.dist-info/WHEEL
lnbits-1.4.1.dist-info/entry_points.txt
lnbits-1.4.1.dist-info/licenses/LICENSE
lnbits-1.4.1.dist-info/RECORD
