Metadata-Version: 2.4
Name: lnbits
Version: 1.4.1
Summary: LNbits, free and open-source Lightning wallet and accounts system.
Project-URL: Homepage, https://lnbits.com
Project-URL: Repository, https://github.com/lnbits/lnbits
Author-email: Alan Bits <alan@lnbits.com>
License-File: LICENSE
Requires-Python: <3.13,>=3.10
Requires-Dist: aiosqlite==0.21.0
Requires-Dist: asyncpg==0.30.0
Requires-Dist: bcrypt==4.3.0
Requires-Dist: bech32==1.2.0
Requires-Dist: bolt11==2.1.1
Requires-Dist: click==8.2.1
Requires-Dist: ecdsa==0.19.1
Requires-Dist: embit==0.8.0
Requires-Dist: fastapi-sso==0.19.0
Requires-Dist: fastapi==0.116.1
Requires-Dist: filetype==1.2.0
Requires-Dist: greenlet<4.0.0,>=3.3.0
Requires-Dist: grpcio==1.69.0
Requires-Dist: httpx==0.27.0
Requires-Dist: itsdangerous==2.2.0
Requires-Dist: jinja2==3.1.6
Requires-Dist: jsonpath-ng==1.7.0
Requires-Dist: lnurl==0.8.3
Requires-Dist: loguru==0.7.3
Requires-Dist: nostr-sdk==0.42.1
Requires-Dist: packaging==25.0
Requires-Dist: pillow>=12.0.0
Requires-Dist: protobuf==5.29.5
Requires-Dist: pycryptodomex==3.23.0
Requires-Dist: pydantic==1.10.22
Requires-Dist: pyjwt==2.10.1
Requires-Dist: pyln-client==25.5
Requires-Dist: pynostr==0.6.2
Requires-Dist: pyqrcode==1.2.1
Requires-Dist: python-crontab==3.2.0
Requires-Dist: python-dotenv>=1.2.1
Requires-Dist: python-multipart==0.0.20
Requires-Dist: pywebpush==2.0.3
Requires-Dist: shortuuid==1.0.13
Requires-Dist: slowapi==0.1.9
Requires-Dist: sqlalchemy==1.4.54
Requires-Dist: sse-starlette==2.3.6
Requires-Dist: starlette==0.47.1
Requires-Dist: typing-extensions==4.14.0
Requires-Dist: uvicorn==0.34.3
Requires-Dist: uvloop==0.21.0
Requires-Dist: websocket-client==1.8.0
Requires-Dist: websockets==15.0.1
Provides-Extra: breez
Requires-Dist: breez-sdk-liquid==0.11.11; extra == 'breez'
Requires-Dist: breez-sdk==0.8.0; extra == 'breez'
Provides-Extra: liquid
Requires-Dist: wallycore==1.4.0; extra == 'liquid'
Provides-Extra: migration
Requires-Dist: psycopg2-binary==2.9.10; extra == 'migration'
